tagulous/__init__.py
tagulous/admin.py
tagulous/apps.py
tagulous/checks.py
tagulous/constants.py
tagulous/forms.py
tagulous/settings.py
tagulous/utils.py
tagulous/views.py
tagulous/contrib/__init__.py
tagulous/contrib/drf.py
tagulous/management/__init__.py
tagulous/management/commands/__init__.py
tagulous/management/commands/initial_tags.py
tagulous/models/__init__.py
tagulous/models/cast.py
tagulous/models/descriptors.py
tagulous/models/fields.py
tagulous/models/initial.py
tagulous/models/managers.py
tagulous/models/migrations.py
tagulous/models/models.py
tagulous/models/options.py
tagulous/models/tagged.py
tagulous/serializers/__init__.py
tagulous/serializers/base.py
tagulous/serializers/json.py
tagulous/serializers/python.py
tagulous/serializers/pyyaml.py
tagulous/serializers/xml_serializer.py
tagulous/signals/__init__.py
tagulous/signals/post.py
tagulous/signals/pre.py
tagulous/static/tagulous/tagulous.js
tagulous/static/tagulous/adaptor/select2-3.js
tagulous/static/tagulous/adaptor/select2-4.js
tagulous/static/tagulous/lib/jquery.js
tagulous/static/tagulous/lib/select2-3/select2-spinner.gif
tagulous/static/tagulous/lib/select2-3/select2.css
tagulous/static/tagulous/lib/select2-3/select2.min.js
tagulous/static/tagulous/lib/select2-3/select2.png
tagulous/static/tagulous/lib/select2-3/select2x2.png
tagulous/static/tagulous/lib/select2-4/css/select2.css
tagulous/static/tagulous/lib/select2-4/css/select2.min.css
tagulous/static/tagulous/lib/select2-4/js/select2.full.js
tagulous/static/tagulous/lib/select2-4/js/select2.full.min.js
tagulous/static/tagulous/lib/select2-4/js/select2.js
tagulous/static/tagulous/lib/select2-4/js/select2.min.js
tagulous/static/tagulous/lib/select2-4/js/i18n/af.js
tagulous/static/tagulous/lib/select2-4/js/i18n/ar.js
tagulous/static/tagulous/lib/select2-4/js/i18n/az.js
tagulous/static/tagulous/lib/select2-4/js/i18n/bg.js
tagulous/static/tagulous/lib/select2-4/js/i18n/bn.js
tagulous/static/tagulous/lib/select2-4/js/i18n/bs.js
django_tagulous-2.1.0.dist-info/LICENSE
django_tagulous-2.1.0.dist-info/METADATA
django_tagulous-2.1.0.dist-info/WHEEL
django_tagulous-2.1.0.dist-info/top_level.txt
django_tagulous-2.1.0.dist-info/RECORD
