Metadata-Version: 2.1
Name: django-tagulous
Version: 2.1.0
Summary: Fabulous Tagging for Django
Author-email: Richard Terry <code@radiac.net>
Project-URL: Homepage, https://radiac.net/projects/django-tagulous/
Project-URL: Documentation, https://django-tagulous.readthedocs.io/
Project-URL: Changelog, https://django-tagulous.readthedocs.io/en/latest/changelog.html
Project-URL: Repository, https://github.com/radiac/django-tagulous
Project-URL: Issues, https://github.com/radiac/django-tagulous/issues
Keywords: django,tags,tagging
Classifier: Development Status :: 5 - Production/Stable
Classifier: Framework :: Django
Classifier: Framework :: Django :: 3.2
Classifier: Framework :: Django :: 4.0
Classifier: Framework :: Django :: 4.1
Classifier: Framework :: Django :: 4.2
Classifier: Framework :: Django :: 5.0
Classifier: Framework :: Django :: 5.1
Classifier: License :: OSI Approved :: BSD License
Classifier: Programming Language :: Python :: 3
Classifier: Operating System :: OS Independent
Requires-Python: >=3.8
License-File: LICENSE
Requires-Dist: Django >=2.2
